mimir_mcp/__init__.py
mimir_mcp/main.py
mimir_mcp-0.1.6.dist-info/licenses/LICENSE
mimir_mcp-0.1.6.dist-info/METADATA
mimir_mcp-0.1.6.dist-info/WHEEL
mimir_mcp-0.1.6.dist-info/entry_points.txt
mimir_mcp-0.1.6.dist-info/top_level.txt
mimir_mcp-0.1.6.dist-info/RECORD
