Metadata-Version: 2.4
Name: mimir-mcp
Version: 0.1.6
Summary: MCP server for Mimir AI
Author-email: Justin Garofolo <justin@trymimir.ai>
License: MIT
Project-URL: Homepage, https://github.com/trymimirai/mimir-mcp
Project-URL: Bug Tracker, https://github.com/trymimirai/mimir-mcp/issues
Project-URL: License, https://github.com/trymimirai/mimir-api/blob/main/LICENSE
Requires-Python: >=3.8
License-File: LICENSE
Requires-Dist: httpx
Requires-Dist: pydantic
Requires-Dist: mcp
Requires-Dist: fastmcp>=2.2.0
Requires-Dist: mimir-api>=0.1.2
Provides-Extra: dev
Requires-Dist: pytest; extra == "dev"
Requires-Dist: black; extra == "dev"
Dynamic: license-file
